LICENSE
README.md
setup.py
src/pylib_sakata/__init__.py
src/pylib_sakata/ctrl.py
src/pylib_sakata/fft.py
src/pylib_sakata/init.py
src/pylib_sakata/kinema.py
src/pylib_sakata/meas.py
src/pylib_sakata/plot.py
src/pylib_sakata/traj.py
src/pylib_sakata.egg-info/PKG-INFO
src/pylib_sakata.egg-info/SOURCES.txt
src/pylib_sakata.egg-info/dependency_links.txt
src/pylib_sakata.egg-info/requires.txt
src/pylib_sakata.egg-info/top_level.txt