Metadata-Version: 2.1
Name: pylib-sakata
Version: 0.3.9
Summary: Control system design and analysis package
Home-page: https://github.com/Koichi-Sakata/pylib_sakata
Author: Koichi Sakata
Author-email: 
Requires-Python: >=3.9,<3.13
License-File: LICENSE
Requires-Dist: numpy==1.26.4
Requires-Dist: scipy==1.14.1
Requires-Dist: matplotlib==3.8.4
Requires-Dist: pandas>=2.2.3
Requires-Dist: control==0.10.1
